domeneshop/__init__.py
domeneshop/client.py
domeneshop-0.4.4.dist-info/LICENSE
domeneshop-0.4.4.dist-info/METADATA
domeneshop-0.4.4.dist-info/WHEEL
domeneshop-0.4.4.dist-info/top_level.txt
domeneshop-0.4.4.dist-info/RECORD
